gravipy/__init__.py
gravipy/tensorial.py
GraviPy-0.2.0.dist-info/AUTHORS
GraviPy-0.2.0.dist-info/LICENSE
GraviPy-0.2.0.dist-info/METADATA
GraviPy-0.2.0.dist-info/WHEEL
GraviPy-0.2.0.dist-info/top_level.txt
GraviPy-0.2.0.dist-info/RECORD
